Pytorch03ZhongwenWendangJiaocheng/README.md
Pytorch03ZhongwenWendangJiaocheng/__init__.py
Pytorch03ZhongwenWendangJiaocheng/__main__.py
Pytorch03ZhongwenWendangJiaocheng/file.epub
Pytorch03ZhongwenWendangJiaocheng/index.html
Pytorch03ZhongwenWendangJiaocheng/css/__init__.py
Pytorch03ZhongwenWendangJiaocheng/css/annotations.css
Pytorch03ZhongwenWendangJiaocheng/css/main.css
Pytorch03ZhongwenWendangJiaocheng/css/normalize.css
Pytorch03ZhongwenWendangJiaocheng/css/popup.css
Pytorch03ZhongwenWendangJiaocheng/font/__init__.py
Pytorch03ZhongwenWendangJiaocheng/font/fontello.eot
Pytorch03ZhongwenWendangJiaocheng/font/fontello.svg
Pytorch03ZhongwenWendangJiaocheng/font/fontello.ttf
Pytorch03ZhongwenWendangJiaocheng/font/fontello.woff
Pytorch03ZhongwenWendangJiaocheng/img/__init__.py
Pytorch03ZhongwenWendangJiaocheng/img/annotator-glyph-sprite.png
Pytorch03ZhongwenWendangJiaocheng/img/annotator-icon-sprite.png
Pytorch03ZhongwenWendangJiaocheng/img/apple-touch-icon.png
Pytorch03ZhongwenWendangJiaocheng/img/cancelfullscreen.png
Pytorch03ZhongwenWendangJiaocheng/img/close.png
Pytorch03ZhongwenWendangJiaocheng/img/fullscreen.png
Pytorch03ZhongwenWendangJiaocheng/img/loader.gif
Pytorch03ZhongwenWendangJiaocheng/img/menu-icon.png
Pytorch03ZhongwenWendangJiaocheng/img/save.png
Pytorch03ZhongwenWendangJiaocheng/img/saved.png
Pytorch03ZhongwenWendangJiaocheng/img/settings-s.png
Pytorch03ZhongwenWendangJiaocheng/img/settings.png
Pytorch03ZhongwenWendangJiaocheng/img/star.png
Pytorch03ZhongwenWendangJiaocheng/js/__init__.py
Pytorch03ZhongwenWendangJiaocheng/js/epub.js
Pytorch03ZhongwenWendangJiaocheng/js/epub.min.js
Pytorch03ZhongwenWendangJiaocheng/js/epub.min.map
Pytorch03ZhongwenWendangJiaocheng/js/hooks.min.js
Pytorch03ZhongwenWendangJiaocheng/js/hooks.min.map
Pytorch03ZhongwenWendangJiaocheng/js/reader.js
Pytorch03ZhongwenWendangJiaocheng/js/reader.js.map
Pytorch03ZhongwenWendangJiaocheng/js/reader.min.js
Pytorch03ZhongwenWendangJiaocheng/js/reader.min.map
pytorch_0_3_zhongwen_wendang_jiaocheng-2024.3.5.0.dist-info/METADATA
pytorch_0_3_zhongwen_wendang_jiaocheng-2024.3.5.0.dist-info/WHEEL
pytorch_0_3_zhongwen_wendang_jiaocheng-2024.3.5.0.dist-info/entry_points.txt
pytorch_0_3_zhongwen_wendang_jiaocheng-2024.3.5.0.dist-info/top_level.txt
pytorch_0_3_zhongwen_wendang_jiaocheng-2024.3.5.0.dist-info/RECORD
